etesync/__init__.py
etesync/api.py
etesync/cache.py
etesync/crypto.py
etesync/db.py
etesync/exceptions.py
etesync/pim.py
etesync/service.py
etesync-0.5.6.dist-info/METADATA
etesync-0.5.6.dist-info/RECORD
etesync-0.5.6.dist-info/WHEEL
etesync-0.5.6.dist-info/top_level.txt
